coolify_cli/__init__.py
coolify_cli/main.py
coolify_cli-0.1.0.dist-info/METADATA
coolify_cli-0.1.0.dist-info/WHEEL
coolify_cli-0.1.0.dist-info/entry_points.txt
coolify_cli-0.1.0.dist-info/RECORD
